quaternary/Quaternary.py
quaternary/__init__.py
python_quaternary-0.0.1.dist-info/LICENSE
python_quaternary-0.0.1.dist-info/METADATA
python_quaternary-0.0.1.dist-info/WHEEL
python_quaternary-0.0.1.dist-info/top_level.txt
python_quaternary-0.0.1.dist-info/RECORD
